lumen_anndata/__init__.py
lumen_anndata/analysis.py
lumen_anndata/app.py
lumen_anndata/cli.py
lumen_anndata/controls.py
lumen_anndata/main.py
lumen_anndata/operations.py
lumen_anndata/py.typed
lumen_anndata/source.py
lumen_anndata/ui.py
lumen_anndata/utils.py
lumen_anndata/views.py
lumen_anndata/embeddings/.gitkeep
lumen_anndata/embeddings/__init__.py
lumen_anndata/embeddings/scanpy.db
lumen_anndata-0.0.2.dist-info/METADATA
lumen_anndata-0.0.2.dist-info/WHEEL
lumen_anndata-0.0.2.dist-info/entry_points.txt
lumen_anndata-0.0.2.dist-info/licenses/LICENSE
lumen_anndata-0.0.2.dist-info/licenses/LICENSE.txt
lumen_anndata-0.0.2.dist-info/RECORD
